main.py
dunkin_ai_assistant-1.0.0.dist-info/METADATA
dunkin_ai_assistant-1.0.0.dist-info/WHEEL
dunkin_ai_assistant-1.0.0.dist-info/entry_points.txt
dunkin_ai_assistant-1.0.0.dist-info/top_level.txt
dunkin_ai_assistant-1.0.0.dist-info/RECORD
